asurso_api/__init__.py
asurso_api/classes/__init__.py
asurso_api/enums/__init__.py
asurso_api/enums/lessons_period.py
asurso_api/enums/mark_value.py
asurso_api/enums/raw.py
asurso_api/exceptions.py
asurso_api/functions/__init__.py
asurso_api/functions/attestation.py
asurso_api/functions/chats.py
asurso_api/functions/dashboard.py
asurso_api/functions/info.py
asurso_api/functions/lessons.py
asurso_api/functions/login.py
asurso_api/functions/logout.py
asurso_api/functions/organization.py
asurso_api/functions/reports.py
asurso_api/typing.py
asurso_api/utils.py
asurso_api-0.6.3.dist-info/METADATA
asurso_api-0.6.3.dist-info/WHEEL
asurso_api-0.6.3.dist-info/RECORD
