Metadata-Version: 2.4
Name: asurso-api
Version: 0.6.3
Summary: API-wrapper for NetSchool (ASURSO)
Author: Alekzum
Author-email: 68947902+Alekzum@users.noreply.github.com
Requires-Python: >=3.8,<4.0
Classifier: Programming Language :: Python :: 3
Classifier: Programming Language :: Python :: 3.8
Classifier: Programming Language :: Python :: 3.9
Classifier: Programming Language :: Python :: 3.10
Classifier: Programming Language :: Python :: 3.11
Classifier: Programming Language :: Python :: 3.12
Classifier: Programming Language :: Python :: 3.13
Classifier: Programming Language :: Python :: 3.14
Requires-Dist: httpx (==0.28.1)
Requires-Dist: pydantic (==2.10.6)
Requires-Dist: python-dotenv (==1.0.1)
